quicpro/__init__.py
quicpro/client.py
quicpro/config.py
quicpro/response.py
quicpro/exceptions/__init__.py
quicpro/exceptions/connection_errors.py
quicpro/exceptions/decoding_error.py
quicpro/exceptions/decryption_error.py
quicpro/exceptions/encoding_error.py
quicpro/exceptions/encryption_error.py
quicpro/exceptions/header_errors.py
quicpro/exceptions/http3_frame_error.py
quicpro/exceptions/http_status_error.py
quicpro/exceptions/packet_errors.py
quicpro/exceptions/pipeline_error.py
quicpro/exceptions/quic_frame_reassembly_error.py
quicpro/exceptions/stream_errors.py
quicpro/exceptions/transmission_error.py
quicpro/exceptions/transport_errors.py
quicpro/model/__init__.py
quicpro/model/message.py
quicpro/model/tls_config.py
quicpro/receiver/__init__.py
quicpro/receiver/consumer_app.py
quicpro/receiver/decoder.py
quicpro/receiver/http3_receiver.py
quicpro/receiver/quic_receiver.py
quicpro/receiver/tls_decryptor.py
quicpro/receiver/udp_receiver.py
quicpro/sender/__init__.py
quicpro/sender/encoder.py
quicpro/sender/http3_sender.py
quicpro/sender/network.py
quicpro/sender/producer_app.py
quicpro/sender/quic_sender.py
quicpro/sender/tls_encryptor.py
quicpro/sender/udp_sender.py
quicpro/utils/__init__.py
quicpro/utils/logging_setup.py
quicpro/utils/event_loop/__init__.py
quicpro/utils/event_loop/base_loop.py
quicpro/utils/event_loop/sync_loop.py
quicpro/utils/event_loop/thread_pool.py
quicpro/utils/http3/__init__.py
quicpro/utils/http3/connection/__init__.py
quicpro/utils/http3/connection/http3_connection.py
quicpro/utils/http3/frames/__init__.py
quicpro/utils/http3/frames/control_frame.py
quicpro/utils/http3/frames/frame.py
quicpro/utils/http3/frames/push_frame.py
quicpro/utils/http3/protocol/__init__.py
quicpro/utils/http3/protocol/constants.py
quicpro/utils/http3/protocol/settings.py
quicpro/utils/http3/qpack/__init__.py
quicpro/utils/http3/qpack/decoder.py
quicpro/utils/http3/qpack/dynamic_table.py
quicpro/utils/http3/qpack/encoder.py
quicpro-1.0.0.dist-info/licenses/LICENSE
quicpro-1.0.0.dist-info/METADATA
quicpro-1.0.0.dist-info/WHEEL
quicpro-1.0.0.dist-info/top_level.txt
quicpro-1.0.0.dist-info/RECORD
