Metadata-Version: 2.4
Name: quicpro
Version: 1.0.0
Summary: A synchronous HTTP/3 client library built on QUIC, UDP, and TLS-like encryption without asyncio.
Author: Jochen Schultz
Author-email: js@intelligent-intern.com
Classifier: Programming Language :: Python :: 3
Classifier: Operating System :: OS Independent
Requires-Python: >=3.6
License-File: LICENSE
Requires-Dist: cryptography
Dynamic: author
Dynamic: author-email
Dynamic: classifier
Dynamic: license-file
Dynamic: requires-dist
Dynamic: requires-python
Dynamic: summary
